mdwiki/__init__.py
mdwiki/config.json
mdwiki/mdwiki.py
mdwiki/mdx_alignmath.py
mdwiki/mdx_eqnmath.py
mdwiki/mdx_mathjax.py
mdwiki/bin/mdpub
mdwiki/bin/mdwiki_exec
mdwiki/templates/default/detail.html
mdwiki/templates/default/footer.html
mdwiki/templates/default/index.html
mdwiki/templates/default/layout.html
mdwiki/templates/default/tag.html
mdwiki/templates/default/css/code_hilighting.css
mdwiki/templates/default/css/mytheme.css
mdwiki/templates/default/css/pages.css
mdwiki/templates/default/css/simple.css
mdwiki/templates/default/image/.keep
mdwiki/templates/default/js/MathJax.js
mdwiki-0.3.0.data/scripts/mdpub
mdwiki-0.3.0.data/scripts/mdwiki_exec
mdwiki-0.3.0.dist-info/METADATA
mdwiki-0.3.0.dist-info/WHEEL
mdwiki-0.3.0.dist-info/top_level.txt
mdwiki-0.3.0.dist-info/RECORD
