Metadata-Version: 2.1
Name: mdwiki
Version: 0.3.0
Summary: zero config static blog builder
Home-page: https://github.com/drunkpig/mdwiki
Author: niceMachine
Author-email: xuchaoo@gmail.com
License: UNKNOWN
Platform: UNKNOWN
Classifier: Programming Language :: Python :: 3
Classifier: License :: OSI Approved :: MIT License
Classifier: Operating System :: OS Independent
Requires-Python: >=3.7
Requires-Dist: markdown
Requires-Dist: Pygments (==2.5.2)
Requires-Dist: beautifulsoup4 (==4.6.3)
Requires-Dist: Jinja2 (>=2.10.1)
Requires-Dist: lxml
Requires-Dist: py-gfm
